synapse_pay_rest/__init__.py
synapse_pay_rest/client.py
synapse_pay_rest/errors.py
synapse_pay_rest/http_client.py
synapse_pay_rest/api/__init__.py
synapse_pay_rest/api/atms.py
synapse_pay_rest/api/client.py
synapse_pay_rest/api/institutions.py
synapse_pay_rest/api/nodes.py
synapse_pay_rest/api/statements.py
synapse_pay_rest/api/subnets.py
synapse_pay_rest/api/subscriptions.py
synapse_pay_rest/api/trans.py
synapse_pay_rest/api/users.py
synapse_pay_rest/models/__init__.py
synapse_pay_rest/models/atms/__init__.py
synapse_pay_rest/models/atms/atm.py
synapse_pay_rest/models/institutions/__init__.py
synapse_pay_rest/models/institutions/institution.py
synapse_pay_rest/models/issue_public_keys/__init__.py
synapse_pay_rest/models/issue_public_keys/issue_public_key.py
synapse_pay_rest/models/nodes/__init__.py
synapse_pay_rest/models/nodes/ach_us_node.py
synapse_pay_rest/models/nodes/base_node.py
synapse_pay_rest/models/nodes/card_us_node.py
synapse_pay_rest/models/nodes/check_us_node.py
synapse_pay_rest/models/nodes/clearing_us_node.py
synapse_pay_rest/models/nodes/deposit_us_node.py
synapse_pay_rest/models/nodes/eft_ind_node.py
synapse_pay_rest/models/nodes/eft_np_node.py
synapse_pay_rest/models/nodes/ib_deposit_us_node.py
synapse_pay_rest/models/nodes/ib_subaccount_us_node.py
synapse_pay_rest/models/nodes/interchange_us_node.py
synapse_pay_rest/models/nodes/iou_node.py
synapse_pay_rest/models/nodes/node.py
synapse_pay_rest/models/nodes/reserve_us_node.py
synapse_pay_rest/models/nodes/subaccount_us_node.py
synapse_pay_rest/models/nodes/subcard_us_node.py
synapse_pay_rest/models/nodes/synapse_ind_node.py
synapse_pay_rest/models/nodes/synapse_np_node.py
synapse_pay_rest/models/nodes/synapse_us_node.py
synapse_pay_rest/models/nodes/triumph_subaccount_us_node.py
synapse_pay_rest/models/nodes/wire_int_node.py
synapse_pay_rest/models/nodes/wire_us_node.py
synapse_pay_rest/models/statements/__init__.py
synapse_pay_rest/models/statements/statement.py
synapse_pay_rest_native-3.4.0.dist-info/METADATA
synapse_pay_rest_native-3.4.0.dist-info/WHEEL
synapse_pay_rest_native-3.4.0.dist-info/top_level.txt
synapse_pay_rest_native-3.4.0.dist-info/RECORD
